OBIA4RTM/OBIA4RTM_HOME
OBIA4RTM/__init__.py
OBIA4RTM/install.py
OBIA4RTM/landcover.cfg
OBIA4RTM/obia4rtm_backend.cfg
OBIA4RTM/postgres.ini
OBIA4RTM/processing_api.py
OBIA4RTM/prosail.txt
OBIA4RTM/S2_PreProcessor/__init__.py
OBIA4RTM/S2_PreProcessor/atmospheric.py
OBIA4RTM/S2_PreProcessor/cloud_masking.py
OBIA4RTM/S2_PreProcessor/install_6S.py
OBIA4RTM/S2_PreProcessor/s2_Py6S_attcor.py
OBIA4RTM/S2_PreProcessor/s2_sen2core_attcor.py
OBIA4RTM/SQL/Queries_Functions/apply_inversion.sql
OBIA4RTM/SQL/Queries_Functions/rmse_function.sql
OBIA4RTM/SQL/Tables/create_lai-results_view.sql
OBIA4RTM/SQL/Tables/create_lai-results_view_aggregated.sql
OBIA4RTM/SQL/Tables/create_lai-validation_view.sql
OBIA4RTM/SQL/Tables/create_new_schema.sql
OBIA4RTM/SQL/Tables/inversion_mapping.sql
OBIA4RTM/SQL/Tables/s2_bands.sql
OBIA4RTM/SQL/Tables/s2_inversion_results.sql
OBIA4RTM/SQL/Tables/s2_landuse.sql
OBIA4RTM/SQL/Tables/s2_lookuptable.sql
OBIA4RTM/SQL/Tables/s2_objects.sql
OBIA4RTM/SQL/Tables/scene_metadata.sql
OBIA4RTM/SQL/Tables/setup_obia4rtm_db.sql
OBIA4RTM/configurations/__init__.py
OBIA4RTM/configurations/connect_db.py
OBIA4RTM/configurations/db_management.py
OBIA4RTM/configurations/logger.py
OBIA4RTM/inversion/__init__.py
OBIA4RTM/inversion/distributions.py
OBIA4RTM/inversion/handle_metadata.py
OBIA4RTM/inversion/handle_prosail_cfg.py
OBIA4RTM/inversion/inversion.py
OBIA4RTM/inversion/lookup_table.py
OBIA4RTM/mdata_proc/__init__.py
OBIA4RTM/mdata_proc/get_scene_metadata.py
OBIA4RTM/mdata_proc/handle_gee_metadata.py
OBIA4RTM/mdata_proc/insert_scene_metadata.py
OBIA4RTM/mdata_proc/parse_s2xml.py
OBIA4RTM/setup_db/__init__.py
OBIA4RTM/setup_db/create_schema.py
OBIA4RTM/setup_db/setup_postgres.py
OBIA4RTM/zonal_stats/__init__.py
OBIA4RTM/zonal_stats/get_mean_refl.py
OBIA4RTM/zonal_stats/get_mean_refl_ee.py
OBIA4RTM-1.0.dist-info/LICENSE.md
OBIA4RTM-1.0.dist-info/METADATA
OBIA4RTM-1.0.dist-info/WHEEL
OBIA4RTM-1.0.dist-info/top_level.txt
OBIA4RTM-1.0.dist-info/RECORD
