Metadata-Version: 2.1
Name: OBIA4RTM
Version: 1.0
Summary: Object-Based Image Analysis Tools for Radiative Transfer Modelling
Home-page: https://github.com/lukasValentin/OBIA4RTM
Author: Lukas Graf
Author-email: graflukas@web.de
License: UNKNOWN
Platform: UNKNOWN
Classifier: Programming Language :: Python :: 3
Classifier: Operating System :: OS Independent
